EHT.cp312-win_amd64.pyd
EHT/EHT.c
EHT/EHT.cp312-win_amd64.pyd
EHT-0.0.10.dist-info/METADATA
EHT-0.0.10.dist-info/WHEEL
EHT-0.0.10.dist-info/top_level.txt
EHT-0.0.10.dist-info/RECORD
