Metadata-Version: 2.1
Name: EHT
Version: 0.0.10
Summary: EHT
Author: fourchains_R&D
Author-email: fourchainsrd@gmail.com
Classifier: Programming Language :: Python :: 3
Classifier: Programming Language :: Cython
Classifier: License :: OSI Approved :: MIT License
Classifier: Operating System :: OS Independent
Requires-Python: >=3.6
Requires-Dist: pandas
Requires-Dist: random
